pilotis/__init__.py
pilotis/cli.py
pilotis/commands/__init__.py
pilotis/commands/aws.py
pilotis/commands/copier_utils.py
pilotis/commands/git.py
pilotis/commands/init.py
pilotis/commands/project_slug.py
pilotis/commands/shell_utils.py
pilotis/domain/__init__.py
pilotis/domain/pilotis_project_config.py
pilotis/domain/python_project_config.py
templates/aws/copier.yml
templates/aws/project/infrastructure/.gitignore
templates/aws/project/infrastructure/backend.tf.jinja
templates/aws/project/infrastructure/provider.tf
templates/aws/project/infrastructure/set_aws_credentials.bash.template
templates/aws/project/infrastructure/storage.tf.jinja
templates/aws/project/infrastructure/versions.tf
templates/aws/project/makefiles/data.mk
templates/aws/project/python/docs/aws-data-storage.md
templates/aws/project/scripts/destroy-aws-infrastructure.bash.jinja
templates/git/commons/copier.yml
templates/git/commons/project/.gitignore
templates/git/commons/project/makefiles/docker.mk
templates/git/commons/project/makefiles/git.mk
templates/git/commons/project/workdir/landing/parsed/.gitignore
templates/git/commons/project/workdir/landing/raw/.gitignore
templates/git/commons/project/workdir/use_cases/{{projectSlug}}/datasets/.gitignore
templates/git/commons/project/workdir/use_cases/{{projectSlug}}/exports/.gitignore
templates/git/commons/project/workdir/use_cases/{{projectSlug}}/models/.gitignore
templates/git/github/copier.yml
templates/git/github/project/.gitkeep.jinja
templates/git/gitlab/copier.yml
templates/git/gitlab/project/.gitlab-ci.yml.jinja
templates/init/copier.yml
templates/init/project/{{project_slug}}/Makefile.jinja
templates/init/project/{{project_slug}}/README.md.jinja
templates/init/project/{{project_slug}}/containers/base/Dockerfile
templates/init/project/{{project_slug}}/containers/base/build.sh.jinja
templates/init/project/{{project_slug}}/containers/base/entrypoint.sh
templates/init/project/{{project_slug}}/containers/dash/Dockerfile.jinja
pilotis-0.2.0.dist-info/entry_points.txt
pilotis-0.2.0.dist-info/LICENSE
pilotis-0.2.0.dist-info/WHEEL
pilotis-0.2.0.dist-info/METADATA
pilotis-0.2.0.dist-info/RECORD
